gtirb_live_register_analysis/__init__.py
gtirb_live_register_analysis/abi.py
gtirb_live_register_analysis/analysis.py
gtirb_live_register_analysis/manager.py
gtirb_live_register_analysis/utils.py
gtirb_live_register_analysis-0.0.10.dist-info/LICENSE.txt
gtirb_live_register_analysis-0.0.10.dist-info/METADATA
gtirb_live_register_analysis-0.0.10.dist-info/WHEEL
gtirb_live_register_analysis-0.0.10.dist-info/top_level.txt
gtirb_live_register_analysis-0.0.10.dist-info/RECORD
