Metadata-Version: 2.1
Name: gtirb-live-register-analysis
Version: 0.0.10
Summary: Utilities for dealing with live register analysis in GTIRB functions
Home-page: https://github.com/lin-toto/gtirb-live-register-analysis
Author: Fangzheng Lin
Author-email: csl@lunlimited.net
License: GPLv3
Classifier: Programming Language :: Python :: 3
License-File: LICENSE.txt
Requires-Dist: gtirb
